badgr_lite/__init__.py
badgr_lite/cli.py
badgr_lite/exceptions.py
badgr_lite/helpers.py
badgr_lite/models.py
badgr_lite-1.0.2.dist-info/LICENSE
badgr_lite-1.0.2.dist-info/METADATA
badgr_lite-1.0.2.dist-info/WHEEL
badgr_lite-1.0.2.dist-info/entry_points.txt
badgr_lite-1.0.2.dist-info/top_level.txt
badgr_lite-1.0.2.dist-info/RECORD
