Metadata-Version: 2.1
Name: badgr-lite
Version: 1.0.2
Summary: Automate awarding Badgr (or equivalent) badges to recipients without the overhead of badgr-server
Home-page: https://github.com/glenjarvis/badgr_lite
Author: Glen Jarvis
Author-email: glen@glenjarvis.com
License: MIT license
Keywords: OpenBadge
Platform: UNKNOWN
Classifier: Development Status :: 5 - Production/Stable
Classifier: Intended Audience :: Developers
Classifier: License :: OSI Approved :: MIT License
Classifier: Natural Language :: English
Classifier: Programming Language :: Python :: 3
Classifier: Programming Language :: Python :: 3.5
Classifier: Programming Language :: Python :: 3.6
Classifier: Programming Language :: Python :: 3.7
Classifier: Programming Language :: Python :: 3.8
Requires-Python: !=3.0.*, !=3.1.*, !=3.2.*, !=3.3.*, !=3.4.*
Requires-Dist: Click
Requires-Dist: requests
Requires-Dist: pytz
